DataNinja/__init__.py
DataNinja/data_analysis.py
DataNinja/dataframe.py
DataNinja/visualization.py
DataNinja-0.5.dist-info/METADATA
DataNinja-0.5.dist-info/WHEEL
DataNinja-0.5.dist-info/top_level.txt
DataNinja-0.5.dist-info/RECORD
