Metadata-Version: 2.1
Name: DataNinja
Version: 0.5
Summary: A comprehensive data analysis and visualization toolkit.
Home-page: https://github.com/ShelbyTO/DataNinja
Author: Nicolas Prieur
Author-email: pu-zle@live.fr
Classifier: Development Status :: 3 - Alpha
Classifier: Intended Audience :: Developers
Classifier: License :: OSI Approved :: MIT License
Classifier: Programming Language :: Python :: 3
Requires-Dist: pandas
Requires-Dist: numpy
Requires-Dist: matplotlib
Requires-Dist: missingno
Requires-Dist: ydata-profiling
